saccademodel/__init__.py
saccademodel/em.py
saccademodel/execute.py
saccademodel/interpolate.py
saccademodel/mle.py
saccademodel/preprocess.py
saccademodel/triangle.py
saccademodel/utils.py
saccademodel/version.py
saccademodel-0.1.0.dist-info/DESCRIPTION.rst
saccademodel-0.1.0.dist-info/METADATA
saccademodel-0.1.0.dist-info/RECORD
saccademodel-0.1.0.dist-info/WHEEL
saccademodel-0.1.0.dist-info/metadata.json
saccademodel-0.1.0.dist-info/top_level.txt
