Metadata-Version: 1.0
Name: saccademodel
Version: 0.1.0
Summary: A least-squares optimal method to find the saccadic reaction time and the saccade duration from tracked gaze points
Home-page: https://github.com/infant-cognition-tampere/saccademodel-py
Author: Akseli Palen
Author-email: akseli.palen@gmail.com
License: MIT
Keywords: saccade estimation eye-tracking
Platform: UNKNOWN
Classifier: Development Status :: 4 - Beta
Classifier: Intended Audience :: Developers
Classifier: Intended Audience :: Science/Research
Classifier: Topic :: Scientific/Engineering :: Mathematics
Classifier: Topic :: Scientific/Engineering :: Image Recognition
Classifier: Topic :: Scientific/Engineering :: Human Machine Interfaces
Classifier: License :: OSI Approved :: MIT License
Classifier: Programming Language :: Python :: 2
Classifier: Programming Language :: Python :: 3
Classifier: Operating System :: OS Independent
